setup.py
django_randomslug.egg-info/PKG-INFO
django_randomslug.egg-info/SOURCES.txt
django_randomslug.egg-info/dependency_links.txt
django_randomslug.egg-info/top_level.txt
randomslug/__init__.py
randomslug/app_settings.py
randomslug/models.py
randomslug/validators.py
randomslug/views.py
randomslug/tests/__init__.py
randomslug/tests/models.py