Metadata-Version: 1.0
Name: django-randomslug
Version: 0.1.1
Summary: reusable Django application providing the custom RandomSlugField model field
Home-page: http://github.com/TvrtkoM/django-randomslug
Author: Tvrtko Majstorovic
Author-email: tvrtkom@gmail.com
License: MIT
Platform: UNKNOWN
